[
  {
    "Title": "Professor",
    "Salutation": "Prof."
  },
  {
    "Title": "Professorin",
    "Salutation": "Prof."
  },
  {
    "Title": "Prof.",
    "Salutation": "Prof."
  },
  {
    "Title": "Dr.",
    "Salutation": "Dr."
  },
  {
    "Title": "Dr. rer. nat.",
    "Salutation": "Dr."
  },
  {
    "Title": "Dr. med.",
    "Salutation": "Dr."
  },
  {
    "Title": "Dr. med. dent.",
    "Salutation": "Dr."
  },
  {
    "Title": "Dr. med. vet.",
    "Salutation": "Dr."
  },
  {
    "Title": "Dr. phil.",
    "Salutation": "Dr."
  },
  {
    "Title": "Dr. iur.",
    "Salutation": "Dr."
  },
  {
    "Title": "Dr. oec.",
    "Salutation": "Dr."
  },
  {
    "Title": "Dr. oec. publ.",
    "Salutation": "Dr."
  },
  {
    "Title": "Dr. h.c.",
    "Salutation": "Dr."
  },
  {
    "Title": "Dr. e.h.",
    "Salutation": "Dr."
  },
  {
    "Title": "Dr. mult.",
    "Salutation": "Dr."
  },
  {
    "Title": "Dr. des.",
    "Salutation": "Dr."
  },
  {
    "Title": "Dr. habil.",
    "Salutation": "Dr."
  },
  {
    "Title": "Doktor",
    "Salutation": "Dr."
  },
  {
    "Title": "Doctor",
    "Salutation": "Dr."
  },
  {
    "Title": "Dipl.-Ing.",
    "Salutation": ""
  },
  {
    "Title": "Dipl. Ing.",
    "Salutation": ""
  },
  {
    "Title": "Diplom-Ingenieur",
    "Salutation": ""
  },
  {
    "Title": "M. Sc.",
    "Salutation": ""
  },
  {
    "Title": "M.Sc.",
    "Salutation": ""
  },
  {
    "Title": "B. Sc.",
    "Salutation": ""
  },
  {
    "Title": "B.Sc.",
    "Salutation": ""
  }
]
